sudokuapi/__init__.py
sudokuapi/sudokuapi.py
sudokuapi-1.1.0.dist-info/LICENSE
sudokuapi-1.1.0.dist-info/METADATA
sudokuapi-1.1.0.dist-info/WHEEL
sudokuapi-1.1.0.dist-info/top_level.txt
sudokuapi-1.1.0.dist-info/RECORD
